yuantao_fmk/__init__.py
yuantao_fmk/downloader/__init__.py
yuantao_fmk/executor/__init__.py
yuantao_fmk/impl/__init__.py
yuantao_fmk/impl/docker_image_loader/__init__.py
yuantao_fmk/impl/run_package_installer/__init__.py
yuantao_fmk/impl/run_package_installer/cann_community_installer.py
yuantao_fmk/resource_installer/__init__.py
yuantao_fmk/utils/__init__.py
yuantao_fmk/utils/decorator.py
yuantao_fmk-0.2.0a7.dist-info/licenses/LICENSE
yuantao_fmk-0.2.0a7.dist-info/METADATA
yuantao_fmk-0.2.0a7.dist-info/WHEEL
yuantao_fmk-0.2.0a7.dist-info/top_level.txt
yuantao_fmk-0.2.0a7.dist-info/RECORD
