Metadata-Version: 2.4
Name: yuantao-fmk
Version: 0.2.0a7
Summary: Add your description here
Requires-Python: >=3.8
License-File: LICENSE
Requires-Dist: alive-progress<3.2
Requires-Dist: hdfs>=2.7.3
Requires-Dist: requests>=2.32.4
Dynamic: license-file
